{
  "rows": [
    {
      "symbol": "2330",
      "market": "twse",
      "name": "台積電",
      "price": 2300,
      "changePercent": 1.3215859030837005,
      "dollarVolume": 93104987424,
      "marketCap": 59644451154100,
      "sector": "半導體業",
      "theme": "CoWoS 先進封裝",
      "isNew": false,
      "rankChange": 1,
      "streak": 49
    },
    {
      "symbol": "2454",
      "market": "twse",
      "name": "聯發科",
      "price": 4640,
      "changePercent": 8.792497069167643,
      "dollarVolume": 84883094150,
      "marketCap": 7442074688480,
      "sector": "半導體業",
      "theme": "IC 設計",
      "isNew": false,
      "rankChange": -1,
      "streak": 49
    },
    {
      "symbol": "2344",
      "market": "twse",
      "name": "華邦電",
      "price": 155,
      "changePercent": 9.929078014184398,
      "dollarVolume": 67328902619,
      "marketCap": 697500029915,
      "sector": "半導體業",
      "theme": "記憶體",
      "isNew": false,
      "rankChange": 1,
      "streak": 49
    },
    {
      "symbol": "2408",
      "market": "twse",
      "name": "南亞科",
      "price": 312,
      "changePercent": 2.800658978583196,
      "dollarVolume": 66247740234,
      "marketCap": 1076464238928,
      "sector": "半導體業",
      "theme": "記憶體",
      "isNew": false,
      "rankChange": 1,
      "streak": 49
    },
    {
      "symbol": "3481",
      "market": "twse",
      "name": "群創",
      "price": 50.2,
      "changePercent": 9.846827133479213,
      "dollarVolume": 65769751304,
      "marketCap": 401057706317.4,
      "sector": "光電業",
      "theme": "面板",
      "isNew": false,
      "rankChange": -2,
      "streak": 2
    },
    {
      "symbol": "2303",
      "market": "twse",
      "name": "聯電",
      "price": 143.5,
      "changePercent": 9.961685823754788,
      "dollarVolume": 40005385051,
      "marketCap": 1804797328845,
      "sector": "半導體業",
      "theme": "晶圓代工",
      "isNew": false,
      "rankChange": 0,
      "streak": 30
    },
    {
      "symbol": "2337",
      "market": "twse",
      "name": "旺宏",
      "price": 155.5,
      "changePercent": -3.115264797507788,
      "dollarVolume": 39615087835,
      "marketCap": 308093521510,
      "sector": "半導體業",
      "theme": "記憶體",
      "isNew": false,
      "rankChange": 4,
      "streak": 34
    },
    {
      "symbol": "2308",
      "market": "twse",
      "name": "台達電",
      "price": 2520,
      "changePercent": 7.234042553191489,
      "dollarVolume": 35478124000,
      "marketCap": 6545809189080,
      "sector": "電子零組件業",
      "theme": "電源管理",
      "isNew": false,
      "rankChange": 2,
      "streak": 49
    },
    {
      "symbol": "6770",
      "market": "twse",
      "name": "力積電",
      "price": 74.8,
      "changePercent": 5.649717514124294,
      "dollarVolume": 31098396635,
      "marketCap": 317436517882,
      "sector": "半導體業",
      "theme": "記憶體",
      "isNew": false,
      "rankChange": 5,
      "streak": 4
    },
    {
      "symbol": "2449",
      "market": "twse",
      "name": "京元電子",
      "price": 315.5,
      "changePercent": -6.794682422451995,
      "dollarVolume": 30805625536,
      "marketCap": 385776068007.5,
      "sector": "半導體業",
      "theme": "IC 封測",
      "isNew": false,
      "rankChange": -1,
      "streak": 32
    },
    {
      "symbol": "3037",
      "market": "twse",
      "name": "欣興",
      "price": 1080,
      "changePercent": -0.4608294930875576,
      "dollarVolume": 29657618700,
      "marketCap": 1715982792480,
      "sector": "電子零組件業",
      "theme": "ABF 載板",
      "isNew": false,
      "rankChange": -4,
      "streak": 23
    },
    {
      "symbol": "6239",
      "market": "twse",
      "name": "力成",
      "price": 340.5,
      "changePercent": -0.43859649122807015,
      "dollarVolume": 26273398362,
      "marketCap": 258489428877,
      "sector": "半導體業",
      "theme": "IC 封測",
      "isNew": false,
      "rankChange": 6,
      "streak": 2
    },
    {
      "symbol": "4958",
      "market": "twse",
      "name": "臻鼎-KY",
      "price": 532,
      "changePercent": -1.4814814814814816,
      "dollarVolume": 23457288000,
      "marketCap": 574251894860,
      "sector": "電子零組件業",
      "theme": "PCB",
      "isNew": false,
      "rankChange": 3,
      "streak": 44
    },
    {
      "symbol": "2313",
      "market": "twse",
      "name": "華通",
      "price": 282,
      "changePercent": -0.8787346221441126,
      "dollarVolume": 22916958378,
      "marketCap": 336093406098,
      "sector": "電子零組件業",
      "theme": "PCB",
      "isNew": false,
      "rankChange": -1,
      "streak": 49
    },
    {
      "symbol": "3189",
      "market": "twse",
      "name": "景碩",
      "price": 702,
      "changePercent": 0.8620689655172413,
      "dollarVolume": 22202080119,
      "marketCap": 369894863520,
      "sector": "半導體業",
      "theme": "ABF 載板",
      "isNew": false,
      "rankChange": -7,
      "streak": 2
    },
    {
      "symbol": "8046",
      "market": "twse",
      "name": "南電",
      "price": 905,
      "changePercent": -1.843817787418655,
      "dollarVolume": 21108481350,
      "marketCap": 584779765735,
      "sector": "電子零組件業",
      "theme": "ABF 載板",
      "isNew": false,
      "rankChange": 1,
      "streak": 49
    },
    {
      "symbol": "2317",
      "market": "twse",
      "name": "鴻海",
      "price": 264,
      "changePercent": 1.9305019305019304,
      "dollarVolume": 20785977986,
      "marketCap": 3696898444536,
      "sector": "其他電子業",
      "theme": "AI 伺服器",
      "isNew": false,
      "rankChange": 9,
      "streak": 49
    },
    {
      "symbol": "3711",
      "market": "twse",
      "name": "日月光投控",
      "price": 642,
      "changePercent": 5.073649754500818,
      "dollarVolume": 19409671301,
      "marketCap": 2863854838644,
      "sector": "半導體業",
      "theme": "IC 封測",
      "isNew": false,
      "rankChange": -3,
      "streak": 43
    },
    {
      "symbol": "2327",
      "market": "twse",
      "name": "國巨*",
      "price": 701,
      "changePercent": 6.051437216338881,
      "dollarVolume": 17741177104,
      "marketCap": 1452097304284,
      "sector": "電子零組件業",
      "theme": "被動元件",
      "isNew": false,
      "rankChange": 0,
      "streak": 35
    },
    {
      "symbol": "2301",
      "market": "twse",
      "name": "光寶科",
      "price": 246,
      "changePercent": 2.7139874739039667,
      "dollarVolume": 14493912668,
      "marketCap": 569762509698,
      "sector": "電腦及週邊設備業",
      "theme": "電源管理",
      "isNew": false,
      "rankChange": 4,
      "streak": 3
    },
    {
      "symbol": "3443",
      "market": "twse",
      "name": "創意",
      "price": 5100,
      "changePercent": -3.5004730368968775,
      "dollarVolume": 14423055640,
      "marketCap": 683460746100,
      "sector": "半導體業",
      "theme": "IP 矽智財",
      "isNew": false,
      "rankChange": 13,
      "streak": 18
    },
    {
      "symbol": "6274",
      "market": "tpex",
      "name": "台燿",
      "price": 1430,
      "changePercent": -3.050847457627119,
      "dollarVolume": 14102811545,
      "marketCap": 412947730910,
      "sector": "電子零組件業",
      "theme": "PCB",
      "isNew": false,
      "rankChange": 6,
      "streak": 49
    },
    {
      "symbol": "2382",
      "market": "twse",
      "name": "廣達",
      "price": 312,
      "changePercent": -1.4218009478672986,
      "dollarVolume": 13793091700,
      "marketCap": 1205139758784,
      "sector": "電腦及週邊設備業",
      "theme": "AI 伺服器",
      "isNew": false,
      "rankChange": 2,
      "streak": 10
    },
    {
      "symbol": "6442",
      "market": "twse",
      "name": "光聖",
      "price": 2040,
      "changePercent": -9.933774834437086,
      "dollarVolume": 13638778765,
      "marketCap": 159269507520,
      "sector": "通信網路業",
      "theme": "光通訊",
      "isNew": false,
      "rankChange": -1,
      "streak": 4
    },
    {
      "symbol": "2383",
      "market": "twse",
      "name": "台光電",
      "price": 5305,
      "changePercent": 0.28355387523629494,
      "dollarVolume": 12711050610,
      "marketCap": 1900893509770,
      "sector": "電子零組件業",
      "theme": "PCB",
      "isNew": false,
      "rankChange": -3,
      "streak": 49
    },
    {
      "symbol": "2409",
      "market": "twse",
      "name": "友達",
      "price": 21.8,
      "changePercent": -0.9090909090909092,
      "dollarVolume": 12131631799,
      "marketCap": 164526757589.6,
      "sector": "光電業",
      "theme": "面板",
      "isNew": false,
      "rankChange": -6,
      "streak": 2
    },
    {
      "symbol": "3017",
      "market": "twse",
      "name": "奇鋐",
      "price": 2700,
      "changePercent": -0.9174311926605505,
      "dollarVolume": 12112986195,
      "marketCap": 1059866118900,
      "sector": "電腦及週邊設備業",
      "theme": "散熱",
      "isNew": false,
      "rankChange": -6,
      "streak": 49
    },
    {
      "symbol": "3653",
      "market": "twse",
      "name": "健策",
      "price": 3670,
      "changePercent": 0,
      "dollarVolume": 12032455565,
      "marketCap": 538509387010,
      "sector": "電子零組件業",
      "theme": "散熱",
      "isNew": true,
      "rankChange": null,
      "streak": 1
    },
    {
      "symbol": "3661",
      "market": "twse",
      "name": "世芯-KY",
      "price": 4500,
      "changePercent": -3.0172413793103448,
      "dollarVolume": 11716485260,
      "marketCap": 369411030000,
      "sector": "半導體業",
      "theme": "IP 矽智財",
      "isNew": false,
      "rankChange": 12,
      "streak": 33
    },
    {
      "symbol": "1303",
      "market": "twse",
      "name": "南亞",
      "price": 95.5,
      "changePercent": 5.176211453744494,
      "dollarVolume": 11709758389,
      "marketCap": 757393461749.5,
      "sector": "塑膠工業",
      "theme": "塑化",
      "isNew": false,
      "rankChange": 9,
      "streak": 2
    },
    {
      "symbol": "8299",
      "market": "tpex",
      "name": "群聯",
      "price": 2310,
      "changePercent": 5,
      "dollarVolume": 11649726320,
      "marketCap": 510708075570,
      "sector": "半導體業",
      "theme": "記憶體",
      "isNew": false,
      "rankChange": 0,
      "streak": 49
    },
    {
      "symbol": "1802",
      "market": "twse",
      "name": "台玻",
      "price": 72.8,
      "changePercent": 0.8310249307479223,
      "dollarVolume": 11183659823,
      "marketCap": 211706826240,
      "sector": "玻璃陶瓷",
      "theme": "玻璃",
      "isNew": false,
      "rankChange": -20,
      "streak": 4
    },
    {
      "symbol": "2481",
      "market": "twse",
      "name": "強茂",
      "price": 147.5,
      "changePercent": 0.3401360544217687,
      "dollarVolume": 11077038144,
      "marketCap": 56361951732.5,
      "sector": "半導體業",
      "theme": "二極體",
      "isNew": false,
      "rankChange": 13,
      "streak": 8
    },
    {
      "symbol": "6223",
      "market": "tpex",
      "name": "旺矽",
      "price": 6485,
      "changePercent": 6.486042692939245,
      "dollarVolume": 10988782290,
      "marketCap": 635408788865,
      "sector": "半導體業",
      "theme": "半導體設備",
      "isNew": false,
      "rankChange": -2,
      "streak": 49
    },
    {
      "symbol": "2345",
      "market": "twse",
      "name": "智邦",
      "price": 2620,
      "changePercent": 0,
      "dollarVolume": 10383502215,
      "marketCap": 1470128890140,
      "sector": "通信網路業",
      "theme": "網通",
      "isNew": false,
      "rankChange": 3,
      "streak": 49
    },
    {
      "symbol": "6669",
      "market": "twse",
      "name": "緯穎",
      "price": 5075,
      "changePercent": -3.882575757575758,
      "dollarVolume": 10350476525,
      "marketCap": 943142014325,
      "sector": "電腦及週邊設備業",
      "theme": "AI 伺服器",
      "isNew": false,
      "rankChange": -9,
      "streak": 31
    },
    {
      "symbol": "2881",
      "market": "twse",
      "name": "富邦金",
      "price": 110,
      "changePercent": 6.280193236714976,
      "dollarVolume": 10347893025,
      "marketCap": 1540810144720,
      "sector": "金融保險",
      "theme": "金融",
      "isNew": false,
      "rankChange": -2,
      "streak": 2
    },
    {
      "symbol": "4919",
      "market": "twse",
      "name": "新唐",
      "price": 206.5,
      "changePercent": -2.132701421800948,
      "dollarVolume": 9686354192,
      "marketCap": 86681527842,
      "sector": "半導體業",
      "theme": "MCU 微控制器",
      "isNew": false,
      "rankChange": -9,
      "streak": 5
    },
    {
      "symbol": "6285",
      "market": "twse",
      "name": "啟碁",
      "price": 311.5,
      "changePercent": 2.2988505747126435,
      "dollarVolume": 9143550657,
      "marketCap": 150661248468.5,
      "sector": "通信網路業",
      "theme": "網通",
      "isNew": true,
      "rankChange": null,
      "streak": 1
    },
    {
      "symbol": "3105",
      "market": "tpex",
      "name": "穩懋",
      "price": 505,
      "changePercent": 4.880581516095535,
      "dollarVolume": 9119878876,
      "marketCap": 214089893920,
      "sector": "半導體業",
      "theme": "PA 功率放大器",
      "isNew": false,
      "rankChange": 0,
      "streak": 49
    },
    {
      "symbol": "3450",
      "market": "twse",
      "name": "聯鈞",
      "price": 501,
      "changePercent": -5.471698113207547,
      "dollarVolume": 8901407729,
      "marketCap": 72986372382,
      "sector": "半導體業",
      "theme": "光通訊",
      "isNew": true,
      "rankChange": null,
      "streak": 1
    },
    {
      "symbol": "8150",
      "market": "twse",
      "name": "南茂",
      "price": 93.9,
      "changePercent": 9.953161592505854,
      "dollarVolume": 8296704213,
      "marketCap": 66154721531.4,
      "sector": "半導體業",
      "theme": "IC 封測",
      "isNew": true,
      "rankChange": null,
      "streak": 1
    },
    {
      "symbol": "6147",
      "market": "tpex",
      "name": "頎邦",
      "price": 224,
      "changePercent": 0.6741573033707865,
      "dollarVolume": 8253755435,
      "marketCap": 166788952736,
      "sector": "半導體業",
      "theme": "驅動 IC",
      "isNew": false,
      "rankChange": 1,
      "streak": 49
    },
    {
      "symbol": "2368",
      "market": "twse",
      "name": "金像電",
      "price": 1375,
      "changePercent": -4.844290657439446,
      "dollarVolume": 8012579530,
      "marketCap": 710939537000,
      "sector": "電子零組件業",
      "theme": "PCB",
      "isNew": false,
      "rankChange": -1,
      "streak": 11
    },
    {
      "symbol": "6531",
      "market": "twse",
      "name": "愛普*",
      "price": 1080,
      "changePercent": 0,
      "dollarVolume": 7688914030,
      "marketCap": 175724134560,
      "sector": "半導體業",
      "theme": "IP 矽智財",
      "isNew": false,
      "rankChange": -12,
      "streak": 2
    },
    {
      "symbol": "3006",
      "market": "twse",
      "name": "晶豪科",
      "price": 241,
      "changePercent": 4.103671706263499,
      "dollarVolume": 7588345936,
      "marketCap": 71755698608,
      "sector": "半導體業",
      "theme": "記憶體",
      "isNew": true,
      "rankChange": null,
      "streak": 1
    },
    {
      "symbol": "1717",
      "market": "twse",
      "name": "長興",
      "price": 84.5,
      "changePercent": 1.8072289156626504,
      "dollarVolume": 7557873657,
      "marketCap": 99054743313.5,
      "sector": "化學工業",
      "theme": "特用化學",
      "isNew": true,
      "rankChange": null,
      "streak": 1
    },
    {
      "symbol": "2603",
      "market": "twse",
      "name": "長榮",
      "price": 211.5,
      "changePercent": 0,
      "dollarVolume": 7227802157,
      "marketCap": 457906593654,
      "sector": "航運業",
      "theme": "航運",
      "isNew": true,
      "rankChange": null,
      "streak": 1
    },
    {
      "symbol": "2360",
      "market": "twse",
      "name": "致茂",
      "price": 2625,
      "changePercent": 5,
      "dollarVolume": 6917361130,
      "marketCap": 1116270072750,
      "sector": "其他電子業",
      "theme": "半導體設備",
      "isNew": false,
      "rankChange": -2,
      "streak": 2
    },
    {
      "symbol": "6415",
      "market": "twse",
      "name": "矽力*-KY",
      "price": 665,
      "changePercent": 5.555555555555555,
      "dollarVolume": 6827946426,
      "marketCap": 258444225445,
      "sector": "半導體業",
      "theme": "IC 設計",
      "isNew": true,
      "rankChange": null,
      "streak": 1
    }
  ],
  "asOf": "2026-05-27T13:30:00+08:00",
  "generatedAt": "2026-06-13T09:08:39.106Z",
  "source": "twse",
  "aiSource": "gemini",
  "themeSummary": [],
  "newEntrants": [],
  "marketBriefing": null,
  "backfilled": true
}